dots/__init__.py
dots/operation/__init__.py
dots/operation/all.py
dots/operation/copy_directory.py
dots/operation/copy_file.py
dots/operation/defer.py
dots/operation/link_directory.py
dots/operation/link_file.py
dots/operation/noop.py
dots/operation/run.py
dots/operation/seq.py
dots/operation/target.py
dots/operation/write_command_output.py
dots/operation/write_file.py
dots/source/__init__.py
dots/source/command.py
dots/source/directory.py
dots/source/file.py
dots/source/shellrc.py
dots/source/string.py
dots/target/__init__.py
dots/target/from_args.py
dots/target/local_diff_target.py
dots/target/local_target.py
dots/target/log.py
dots/target/noop_target.py
dots/target/util.py
dots/util/read_file.py
dots/util/run_command.py
dots/util/run_sync.py
idzhiblavi_libdots-0.0.20.dist-info/licenses/LICENSE
idzhiblavi_libdots-0.0.20.dist-info/METADATA
idzhiblavi_libdots-0.0.20.dist-info/WHEEL
idzhiblavi_libdots-0.0.20.dist-info/top_level.txt
idzhiblavi_libdots-0.0.20.dist-info/RECORD
