Metadata-Version: 2.4
Name: idzhiblavi_libdots
Version: 0.0.20
Summary: Dotfiles management library
Author-email: Ibragim Dzhiblavi <dzhiblavi@gmail.com>
License-File: LICENSE
Requires-Dist: loguru
Requires-Dist: asyncio
Requires-Dist: aiofile
Dynamic: license-file
